flow_compose/__init__.py
flow_compose/a/__init__.py
flow_compose/extensions/__init__.py
flow_compose/extensions/makefun_extension.py
flow_compose/implementation/__init__.py
flow_compose/implementation/classes/__init__.py
flow_compose/implementation/classes/a/__init__.py
flow_compose/implementation/classes/a/flow.py
flow_compose/implementation/classes/a/flow_argument.py
flow_compose/implementation/classes/a/flow_function.py
flow_compose/implementation/classes/a/flow_function_invoker.py
flow_compose/implementation/classes/base/__init__.py
flow_compose/implementation/classes/base/flow.py
flow_compose/implementation/classes/base/flow_argument.py
flow_compose/implementation/classes/base/flow_function.py
flow_compose/implementation/classes/base/flow_function_invoker.py
flow_compose/implementation/classes/flow.py
flow_compose/implementation/classes/flow_argument.py
flow_compose/implementation/classes/flow_function.py
flow_compose/implementation/classes/flow_function_invoker.py
flow_compose/implementation/decorators/__init__.py
flow_compose/implementation/decorators/a/__init__.py
flow_compose/implementation/decorators/a/flow.py
flow_compose/implementation/decorators/a/flow_function.py
flow_compose/implementation/decorators/base/__init__.py
flow_compose/implementation/decorators/base/flow.py
flow_compose/implementation/decorators/base/flow_function.py
flow_compose/implementation/decorators/flow.py
flow_compose/implementation/decorators/flow_function.py
flow_compose/implementation/helpers.py
flow_compose/py.typed
flow_compose/types.py
flow_compose-0.4.0.dist-info/LICENSE
flow_compose-0.4.0.dist-info/METADATA
flow_compose-0.4.0.dist-info/WHEEL
flow_compose-0.4.0.dist-info/RECORD
