Metadata-Version: 2.3
Name: flow-compose
Version: 0.4.0
Summary: Flow Compose - Configurable Function Composition
License: MPL2
Author: Vinko Buble
Author-email: vinkobuble@gmail.com
Requires-Python: >=3.10
Classifier: License :: Other/Proprietary License
Classifier: Programming Language :: Python :: 3
Classifier: Programming Language :: Python :: 3.10
Classifier: Programming Language :: Python :: 3.11
Classifier: Programming Language :: Python :: 3.12
Classifier: Programming Language :: Python :: 3.13
Requires-Dist: makefun (>=1.15.6,<2.0.0)
Project-URL: Homepage, https://github.com/execution-flows/flow-compose
Project-URL: Repository, https://github.com/execution-flows/flow-compose
